{
  "type": "object",
  "properties": {
    "id": { "type": "integer" },
    "name": { "type": "string" },
    "type": { "type": "string" },
    "created_at": { "type": "date" },
    "updated_at": { "type": "date" },
    "breadcrumb": { "type": ["array", "null"] },
    "can_edit": { "type": ["boolean"] },
    "can_edit_content": { "type": ["boolean"] },
    "tag_list": { "type": ["array", "null"] },
    "inherited_tag_list": { "type": ["array", "null"] },
    "cover": { "type": ["object"] },
    "organization_id": { "type": "integer" },
    "is_org_template_collection": { "type": ["boolean"] },
    "is_profile_template": { "type": ["boolean"] },
    "is_profile_collection": { "type": ["boolean"] }
  },
  "required": ["id", "name", "type", "created_at", "cover"]
}
